metodo_FZI.py
metodo_FZI_dawer_y_pasto-0.2.dist-info/METADATA
metodo_FZI_dawer_y_pasto-0.2.dist-info/WHEEL
metodo_FZI_dawer_y_pasto-0.2.dist-info/top_level.txt
metodo_FZI_dawer_y_pasto-0.2.dist-info/RECORD
