Metadata-Version: 2.1
Name: metodo-FZI-dawer-y-pasto
Version: 0.2
Summary: Code for made FZI method
Home-page: UNKNOWN
Author: UNKNOWN
Author-email: UNKNOWN
License: UNKNOWN
Platform: UNKNOWN
